{
  
    "version": 7,
    "message": "เวอร์ชันไฟล์: 7 \nมีอะไรใหม่ \nอัพเดตแก้โฆษนาดับ😘",
    "fileUrl": "https://raw.githubusercontent.com/takza1155/AAAvip/refs/heads/main/fileaaa.json",
    
    "RewardAmount": 24,
    
    "messageWarning":"มีอะไรใหม่ ?\n• อัปเดต UI \n• เพิ่มฟังก์ชัน Hotshare \n• แก้ไขข้อบกพร่องและอื่นๆ อีกมากมาย\n \nขอบคุณที่เข้าใจ❤️",
    "title":"ไม่สามารถใช้เวอร์ชันปัจจุบันต่อได้ คุณต้องอัปเกรด ",
    "link":"https://play.google.com/store/apps/details?id=aaavpn.pro.net",
    "website":"https://play.google.com/store/apps/details?id=aaavpn.pro.net",
    "versionCode": 1,
    
    "files": [
    
    {
    
             "name": "SERVER",
    
             "url": "http"
    
          }
    
    
       ]
      
    }
